ReduceMonomsRBC/__init__.py
ReduceMonomsRBC/constructODEs_quad.py
ReduceMonomsRBC/construct_roms.py
ReduceMonomsRBC/monom_reduction.py
ReduceMonomsRBC/reduce_monoms.py
ReduceMonomsRBC-0.2.dist-info/LICENSE
ReduceMonomsRBC-0.2.dist-info/METADATA
ReduceMonomsRBC-0.2.dist-info/WHEEL
ReduceMonomsRBC-0.2.dist-info/top_level.txt
ReduceMonomsRBC-0.2.dist-info/RECORD
