Metadata-Version: 2.1
Name: ReduceMonomsRBC
Version: 0.2
Summary: Reduce monomial basis for SDP computations for ROM of Rayleigh–Bénard convection.
Home-page: https://github.com/PeriodicROM/ReduceMonomsRBC/
Author: Matt Olson
Author-email: mlolson@umich.edu
License: UNKNOWN
Platform: UNKNOWN
Classifier: Programming Language :: Python :: 3.7
Classifier: License :: OSI Approved :: MIT License
Requires-Dist: ipython (>=6)
Requires-Dist: numpy
Requires-Dist: sympy
Requires-Dist: scipy (>=1.0)
